CODE_OF_CONDUCT.rst
CONTRIBUTING.rst
LICENSE
MANIFEST.in
README.rst
development.txt
pyproject.toml
requirements.txt
setup.cfg
setup.py
uiclasses/__init__.py
uiclasses/base.py
uiclasses/collections.py
uiclasses/errors.py
uiclasses/fs.py
uiclasses/meta.py
uiclasses/typing.py
uiclasses/utils.py
uiclasses/version.py
uiclasses.egg-info/PKG-INFO
uiclasses.egg-info/SOURCES.txt
uiclasses.egg-info/dependency_links.txt
uiclasses.egg-info/entry_points.txt
uiclasses.egg-info/not-zip-safe
uiclasses.egg-info/requires.txt
uiclasses.egg-info/top_level.txt