Metadata-Version: 2.1
Name: uiclasses
Version: 2.4.0
Summary: Data-Modeling for User Interfaces
Home-page: https://github.com/gabrielfalcao/uiclasses
Author: Gabriel Falcao
Author-email: gabriel@nacaolivre.org
Maintainer: Gabriel Falcão
Maintainer-email: gabriel@nacaolivre.org
License: UNKNOWN
Project-URL: Documentation, https://uiclasses.readthedocs.io/en/latest/
Project-URL: Source Code, https://github.com/gabrielfalcao/uiclasses
Project-URL: Issue Tracker, https://github.com/gabrielfalcao/uiclasses/issues
Project-URL: Test Coverage, https://codecov.io/gh/gabrielfalcao/uiclasses
Platform: UNKNOWN
Classifier: Development Status :: 5 - Production/Stable
Classifier: Environment :: Console
Classifier: Environment :: Web Environment
Classifier: Environment :: MacOS X
Classifier: Environment :: Handhelds/PDA's
Classifier: Environment :: Win32 (MS Windows)
Classifier: Environment :: X11 Applications
Classifier: License :: OSI Approved :: MIT License
Classifier: Operating System :: MacOS :: MacOS X
Classifier: Operating System :: POSIX :: Linux
Classifier: Programming Language :: Python :: 3.6
Classifier: Programming Language :: Python :: 3.7
Classifier: Programming Language :: Python :: Implementation :: CPython
Requires-Python: >=3.6
License-File: LICENSE
